LICENSE
README.md
pyproject.toml
setup.cfg
auto_gitlab/__init__.py
auto_gitlab/apps.py
auto_gitlab/enums.py
auto_gitlab/gitlab_instance.py
auto_gitlab/gitlab_manager.py
auto_gitlab/permissions.py
auto_gitlab/urls.py
auto_gitlab/utils.py
auto_gitlab/views.py
auto_gitlab/config/__init__.py
auto_gitlab/config/app_config.py
auto_gitlab/config/app_config_instance.py
auto_gitlab/config/config_schema.py
auto_gitlab/config/constants.py
auto_gitlab/config/exceptions.py
auto_gitlab/config/parser.py
django_auto_gitlab.egg-info/PKG-INFO
django_auto_gitlab.egg-info/SOURCES.txt
django_auto_gitlab.egg-info/dependency_links.txt
django_auto_gitlab.egg-info/requires.txt
django_auto_gitlab.egg-info/top_level.txt