Metadata-Version: 2.1
Name: django-auto-gitlab
Version: 1.0.0
Summary: Package that helps managing GitLab tasks labels automatically
Home-page: https://github.com/sebastian-jedrzejewski/django-auto-gitlab
Author: Sebastian Jędrzejewski
Author-email: sebastian.jedrzejewski12@gmail.com
Project-URL: Documentation, https://django-auto-gitlab.readthedocs.io/en/latest/
Classifier: Framework :: Django
Classifier: Operating System :: OS Independent
Classifier: License :: OSI Approved :: MIT License
Classifier: Programming Language :: Python
Classifier: Programming Language :: Python :: 3
Classifier: Programming Language :: Python :: 3.8
Classifier: Programming Language :: Python :: 3.9
Classifier: Programming Language :: Python :: 3.10
Classifier: Programming Language :: Python :: 3.11
Requires-Python: >=3.7
License-File: LICENSE
Requires-Dist: django>=3
Requires-Dist: djangorestframework>=3.11
Requires-Dist: python-gitlab
Requires-Dist: pyyaml
Requires-Dist: retrying
Requires-Dist: cerberus
